{
  "Vicuna-7B": {
    "download": {
      "files": {
        "model": "ggml-old-vic7b-q4_0.bin"
      },
      "repo": "https://huggingface.co/eachadea/ggml-vicuna-7b-1.1",
      "commit": "8ea1e83a4f96d60802c2f155036859bb9fbd5349",
      "branch": "main"
    },
    "compatability": {
      "ramGB": 5,
      "cpuCors": 2,
      "compressions": "q4_0"
    },
    "settings": {
      "bind": "node-llama-cpp"
    }
  },
  "Raven-RWKV-7B": {
    "download": {
      "files": {
        "model": "RWKV-4-Raven-1B5-v11-Eng99%25-Other1%25-20230425-ctx4096-16_Q4_2.bin",
        "tokenizer": "20B_tokenizer.json"
      },
      "repo": "https://huggingface.co/imxcstar/rwkv-4-raven-ggml",
      "commit": "d326f4bc3e73c633a481ce74ae82dc859acd4427",
      "branch": "main"
    },
    "compatability": {
      "ramGB": 5,
      "cpuCors": 2,
      "compressions": "q4_0"
    },
    "settings": {
      "bind": "node-llama-rwkv"
    }
  },
  "Bing-Chat": {
    "compatability": {
      "ramGB": 0,
      "cpuCors": 0
    },
    "settings": {
      "bind": "bing-chat"
    }
  }
}